{
  "basics": {
    "name": "Melody Zhao",
    "label": "AI Software Engineer",
    "picture": "https://github.com/Melody-coder923/Melody-coder923.github.io/blob/main/images/avatar.jpg?raw=true",
    "website": "https://melody-coder923.github.io/",
    "summary": "Aspiring AI Engineer | Computer Software Engineering Graduate Student | 56 Countries Traveler | Always Curious & Learning | Open to 2026 Internship",
    "location": {
      "address": "",
      "postalCode": "",
      "city": "Seattle",
      "countryCode": "",
      "region": "Washington"
    },
    "profiles": [
      {
        "network": "github",
        "username": "Melody-coder923",
        "url": "https://github.com/Melody-coder923"
      },
      {
        "network": "linkedin",
        "username": "Melody Zhao",
        "url": "https://www.linkedin.com/in/melody-zhao-092348239/"
      }
    ]
  },
  "interests": [
    {
      "name": "AI Software Development",
      "keywords": []
    },
    {
      "name": "Machine Learning",
      "keywords": []
    },
    {
      "name": "Data Science",
      "keywords": []
    }
  ],
  "skills": [
    {
      "name": "Languages",
      "level": "",
      "keywords": [
        "Python",
        "Java",
        "Typescript/Javascript",
        "Pytorch",
        "JAX",
        "Golang",
        "Shell scripting",
        "HTML",
        "CSS"
      ]
    },
    {
      "name": "Frameworks",
      "level": "",
      "keywords": [
        "Spring",
        "TensorFlow",
        "PyTorch",
        "Symfony",
        "Django",
        "React",
        "Angular"
      ]
    },
    {
      "name": "Tools",
      "level": "",
      "keywords": [
        "AWS",
        "Docker",
        "Kubernetes",
        "Helm",
        "Grafana"
      ]
    }
  ],
  "education": [
    {
      "institution": "Northeastern University",
      "area": "Computer Software Engineering",
      "endDate": "May 2027"
    }
  ]
}
